{
    "0_file": [
        "Сен маған (өте) ұнайсың.",
        "Ты мне (очень) нравишься.",
        "8_26.0.mp3",
        0
    ],
    "1_file": [
        "Мен сені жанымдай жақсы көремін",
        "Я люблю тебя всем сердцем",
        "8_26.1.mp3",
        1
    ],
    "2_file": [
        "Мен сені сүйемін / Мен сені жақсы көремін",
        "Я тебя люблю",
        "8_26.2.mp3",
        2
    ],
    "3_file": [
        "Құшақташы мені",
        "Обними меня",
        "8_26.3.mp3",
        3
    ],
    "4_file": [
        "Сен сондай әдемісің.",
        "Ты очень красивая",
        "8_26.4.mp3",
        4
    ],
    "5_file": [
        "Сені ғана ойлаймын",
        "Думаю только о тебе",
        "8_26.5.mp3",
        5
    ],
    "6_file": [
        "Жаным менің",
        "Душа моя",
        "8_26.6.mp3",
        6
    ],
    "7_file": [
        "Періштем менің",
        "Ты мой ангел",
        "8_26.7.mp3",
        7
    ],
    "8_file": [
        "Жүрегім менің",
        "Сердце мое",
        "8_26.8.mp3",
        8
    ],
    "9_file": [
        "Сенің күлкің мені шексіз бақытты етеді",
        "Твоя улыбка делает меня невероятно счастливым(ой)",
        "8_26.9.mp3",
        9
    ],
    "10_file": [
        "Өзіңді көріп есімнен адастым",
        "Ты сводишь меня с ума",
        "8_26.10.mp3",
        10
    ],
    "11_file": [
        "Телефон соқсам, қалай қарайсың?",
        "Я могу тебе позвонить?",
        "8_26.11.mp3",
        11
    ]
}